swaggapi/__init__.py
swaggapi/build.py
swaggapi/api/__init__.py
swaggapi/api/builder/__init__.py
swaggapi/api/builder/utils.py
swaggapi/api/builder/client/__init__.py
swaggapi/api/builder/client/requester.py
swaggapi/api/builder/common/__init__.py
swaggapi/api/builder/common/fields.py
swaggapi/api/builder/common/model.py
swaggapi/api/builder/common/response.py
swaggapi/api/builder/server/__init__.py
swaggapi/api/builder/server/exceptions.py
swaggapi/api/builder/server/request.py
swaggapi/api/builder/server/response.py
swaggapi/api/openapi/__init__.py
swaggapi/api/openapi/abstract_model.py
swaggapi/api/openapi/models.py
swaggapi/api/openapi/types.py
swaggapi/api/openapi/utils.py
swaggapi-0.6.7.dist-info/LICENSE
swaggapi-0.6.7.dist-info/METADATA
swaggapi-0.6.7.dist-info/WHEEL
swaggapi-0.6.7.dist-info/top_level.txt
swaggapi-0.6.7.dist-info/RECORD
